abstime/__init__.py
abstime-0.0.1a0.dist-info/METADATA
abstime-0.0.1a0.dist-info/WHEEL
abstime-0.0.1a0.dist-info/RECORD
