Metadata-Version: 2.4
Name: abstime
Version: 0.0.1a0
Summary: Early alpha placeholder for the upcoming abstime project.
Author: JIN
License: MIT
Classifier: Development Status :: 3 - Alpha
Classifier: Intended Audience :: Developers
Classifier: License :: OSI Approved :: MIT License
Classifier: Programming Language :: Python :: 3
Classifier: Programming Language :: Python :: 3 :: Only
Requires-Python: >=3.8
